coronacoin.py
coronacoin-1.0.0.dist-info/WHEEL
coronacoin-1.0.0.dist-info/METADATA
coronacoin-1.0.0.dist-info/RECORD
