Metadata-Version: 2.1
Name: coronacoin
Version: 1.0.0
Summary: Библиотека для использования API CoronaCoin
Author: LooPeKa
Author-email: loudmaks10@gmail.com
Requires-Python: >=3.8,<4.0
Classifier: Programming Language :: Python :: 3
Classifier: Programming Language :: Python :: 3.8
Requires-Dist: requests (>=2.23.0,<3.0.0)
